{
  "accounts": {
    "a.lojen@kindle.com": [
      "EPUB",
      false,
      false
    ],
    "pomartel@kindle.com": [
      "EPUB",
      true,
      true
    ]
  },
  "aliases": {
    "a.lojen@kindle.com": "Alexandra",
    "pomartel@kindle.com": "PO"
  },
  "encryption": "TLS",
  "from_": "po@pouding.com",
  "relay_host": "smtp-relay.gmail.com",
  "relay_password": "766778692077747a78206d63787a206d6a646b",
  "relay_port": 587,
  "relay_username": "po@pouding.com",
  "subjects": {},
  "tags": {}
}